{
  "input": {
    "molecule": {
      "cavity_coords": [
        {
          "center": [
            0.0,
            0.0,
            0.0
          ],
          "radius": 1.6629589896706778
        }
      ],
      "cavity_width": 0.37794522492515403,
      "charge": 16,
      "coords": [
        {
          "atom": "ar",
          "xyz": [
            0.0,
            0.0,
            0.0
          ]
        }
      ],
      "multiplicity": 1
    },
    "mpi": {
      "bank_size": -1,
      "numerically_exact": false,
      "shared_memory_size": 10000
    },
    "mra": {
      "basis_order": 11,
      "basis_type": "interpolating",
      "boxes": [
        2,
        2,
        2
      ],
      "corner": [
        -1,
        -1,
        -1
      ],
      "max_scale": 20,
      "min_scale": -5
    },
    "printer": {
      "file_name": "Ar_68.5179945.inp",
      "print_level": 0,
      "print_mpi": false,
      "print_prec": 6,
      "print_width": 75
    },
    "rsp_calculations": {},
    "scf_calculation": {
      "fock_operator": {
        "coulomb_operator": {
          "poisson_prec": 1e-07,
          "shared_memory": false
        },
        "exchange_operator": {
          "exchange_prec": -1.0,
          "poisson_prec": 1e-07
        },
        "kinetic_operator": {
          "derivative": "abgv_55"
        },
        "nuclear_operator": {
          "proj_prec": 1e-07,
          "shared_memory": false,
          "smooth_prec": 1e-07
        },
        "xc_operator": {
          "shared_memory": false,
          "xc_functional": {
            "cutoff": 0.0,
            "functionals": [
              {
                "coef": 1.0,
                "name": "svwn5"
              }
            ],
            "spin": false
          }
        },
        "zora_operator": {
          "derivative": "abgv_00",
          "dev_prefactors": [
            1,
            1
          ],
          "light_speed": 68.5179945,
          "proj_prec": 1e-07,
          "shared_memory": false
        }
      },
      "initial_guess": {
        "file_basis": "initial_guess/mrchem.bas",
        "file_chk": "checkpoint/phi_scf",
        "file_gto_a": "initial_guess/mrchem.moa",
        "file_gto_b": "initial_guess/mrchem.mob",
        "file_gto_p": "initial_guess/mrchem.mop",
        "file_phi_a": "initial_guess/phi_a_scf",
        "file_phi_b": "initial_guess/phi_b_scf",
        "file_phi_p": "initial_guess/phi_p_scf",
        "localize": true,
        "method": "DFT (SVWN5)",
        "prec": 1e-07,
        "restricted": true,
        "type": "mw",
        "zeta": 0
      },
      "properties": {
        "dipole_moment": {
          "dip-1": {
            "operator": "h_e_dip",
            "precision": 1e-07,
            "r_O": [
              0.0,
              0.0,
              0.0
            ]
          }
        }
      },
      "scf_solver": {
        "checkpoint": false,
        "derivative": "abgv_55",
        "energy_thrs": 1e-07,
        "file_chk": "checkpoint/phi_scf",
        "final_prec": 1e-07,
        "helmholtz_prec": -1.0,
        "kain": 10,
        "light_speed": 68.5179945,
        "localize": true,
        "max_iter": 100,
        "method": "DFT (SVWN5)",
        "orbital_thrs": 1e-06,
        "proj_prec": 1e-07,
        "rotation": 5,
        "shared_memory": false,
        "smooth_prec": 1e-07,
        "start_prec": 1e-07
      },
      "write_orbitals": {
        "file_phi_a": "orbitals/phi_a_scf",
        "file_phi_b": "orbitals/phi_b_scf",
        "file_phi_p": "orbitals/phi_p_scf"
      }
    },
    "schema_name": "mrchem_input",
    "schema_version": 1
  },
  "output": {
    "properties": {
      "center_of_mass": [
        0.0,
        0.0,
        0.0
      ],
      "charge": 16,
      "dipole_moment": {
        "dip-1": {
          "magnitude": 3.281326024214634e-10,
          "r_O": [
            0.0,
            0.0,
            0.0
          ],
          "vector": [
            1.888953113608357e-10,
            1.895274957433734e-10,
            1.8991812571479494e-10
          ],
          "vector_el": [
            0.0,
            0.0,
            0.0
          ],
          "vector_nuc": [
            1.8908696269200426e-10,
            1.8972309301144843e-10,
            1.9013289818287748e-10
          ]
        }
      },
      "geometry": [
        {
          "symbol": "Ar",
          "xyz": [
            0.0,
            0.0,
            0.0
          ]
        }
      ],
      "multiplicity": 1,
      "orbital_energies": {
        "energy": [
          -151.50895613377298
        ],
        "occupation": [
          2.0
        ],
        "spin": [
          "p"
        ],
        "sum_occupied": -303.01791226754597
      },
      "scf_energy": {
        "E_ee": 22.959285937861573,
        "E_eext": 0.0,
        "E_el": -322.6704748803035,
        "E_en": -669.6563417250376,
        "E_kin": 334.1285902482364,
        "E_next": 0.0,
        "E_nn": 0.0,
        "E_nuc": 0.0,
        "E_tot": -322.6704748803035,
        "E_x": 0.0,
        "E_xc": -10.102009341363923,
        "Er_el": 0.0,
        "Er_nuc": 0.0,
        "Er_tot": 0.0
      }
    },
    "provenance": {
      "creator": "MRChem",
      "mpi_processes": 32,
      "nthreads": 16,
      "routine": "mrchem.x",
      "total_cores": 512,
      "version": "1.1.0-alpha"
    },
    "rsp_calculations": null,
    "scf_calculation": {
      "initial_energy": {
        "E_ee": 21.987610673690607,
        "E_eext": 0.0,
        "E_el": -321.57348892906765,
        "E_en": -635.2078598797679,
        "E_kin": 301.3177529982763,
        "E_next": 0.0,
        "E_nn": 0.0,
        "E_nuc": 0.0,
        "E_tot": -321.57348892906765,
        "E_x": 0.0,
        "E_xc": -9.670992721266714,
        "Er_el": 0.0,
        "Er_nuc": 0.0,
        "Er_tot": 0.0
      },
      "scf_solver": {
        "converged": true,
        "cycles": [
          {
            "energy_terms": {
              "E_ee": 22.413571589293703,
              "E_eext": 0.0,
              "E_el": -322.3657518304357,
              "E_en": -650.9369519281998,
              "E_kin": 316.0185569236042,
              "E_next": 0.0,
              "E_nn": 0.0,
              "E_nuc": 0.0,
              "E_tot": -322.3657518304357,
              "E_x": 0.0,
              "E_xc": -9.860928415133783,
              "Er_el": 0.0,
              "Er_nuc": 0.0,
              "Er_tot": 0.0
            },
            "energy_total": -322.3657518304357,
            "energy_update": 0.7922629013680762,
            "mo_residual": 0.016050447242793097,
            "wall_time": 14.868204607
          },
          {
            "energy_terms": {
              "E_ee": 22.6668579964575,
              "E_eext": 0.0,
              "E_el": -322.58615103134815,
              "E_en": -659.8070458270764,
              "E_kin": 324.5271960060622,
              "E_next": 0.0,
              "E_nn": 0.0,
              "E_nuc": 0.0,
              "E_tot": -322.58615103134815,
              "E_x": 0.0,
              "E_xc": -9.973159206791447,
              "Er_el": 0.0,
              "Er_nuc": 0.0,
              "Er_tot": 0.0
            },
            "energy_total": -322.58615103134815,
            "energy_update": 0.22039920091242493,
            "mo_residual": 0.009292785690368644,
            "wall_time": 12.569918721
          },
          {
            "energy_terms": {
              "E_ee": 22.80638493726277,
              "E_eext": 0.0,
              "E_el": -322.6465042454377,
              "E_en": -664.5559568934191,
              "E_kin": 329.1378134175527,
              "E_next": 0.0,
              "E_nn": 0.0,
              "E_nuc": 0.0,
              "E_tot": -322.6465042454377,
              "E_x": 0.0,
              "E_xc": -10.034745706834068,
              "Er_el": 0.0,
              "Er_nuc": 0.0,
              "Er_tot": 0.0
            },
            "energy_total": -322.6465042454377,
            "energy_update": 0.060353214089559515,
            "mo_residual": 0.005061608023095812,
            "wall_time": 12.746850936
          },
          {
            "energy_terms": {
              "E_ee": 22.963216469841093,
              "E_eext": 0.0,
              "E_el": -322.6694481136605,
              "E_en": -669.8053380406726,
              "E_kin": 334.276471797216,
              "E_next": 0.0,
              "E_nn": 0.0,
              "E_nuc": 0.0,
              "E_tot": -322.6694481136605,
              "E_x": 0.0,
              "E_xc": -10.103798340044962,
              "Er_el": 0.0,
              "Er_nuc": 0.0,
              "Er_tot": 0.0
            },
            "energy_total": -322.6694481136605,
            "energy_update": 0.022943868222796482,
            "mo_residual": 0.005651442107337693,
            "wall_time": 13.135077136
          },
          {
            "energy_terms": {
              "E_ee": 22.958042422206667,
              "E_eext": 0.0,
              "E_el": -322.6698536198196,
              "E_en": -669.6069728411671,
              "E_kin": 334.0805386689327,
              "E_next": 0.0,
              "E_nn": 0.0,
              "E_nuc": 0.0,
              "E_tot": -322.6698536198196,
              "E_x": 0.0,
              "E_xc": -10.101461869791859,
              "Er_el": 0.0,
              "Er_nuc": 0.0,
              "Er_tot": 0.0
            },
            "energy_total": -322.6698536198196,
            "energy_update": 0.00040550615909751286,
            "mo_residual": 0.0001877227374032264,
            "wall_time": 13.63901011
          },
          {
            "energy_terms": {
              "E_ee": 22.9585838008485,
              "E_eext": 0.0,
              "E_el": -322.6700116372714,
              "E_en": -669.6259913516624,
              "E_kin": 334.099093838582,
              "E_next": 0.0,
              "E_nn": 0.0,
              "E_nuc": 0.0,
              "E_tot": -322.6700116372714,
              "E_x": 0.0,
              "E_xc": -10.101697925039492,
              "Er_el": 0.0,
              "Er_nuc": 0.0,
              "Er_tot": 0.0
            },
            "energy_total": -322.6700116372714,
            "energy_update": 0.00015801745178123383,
            "mo_residual": 2.049826527544585e-05,
            "wall_time": 12.820872446
          },
          {
            "energy_terms": {
              "E_ee": 22.959181747278148,
              "E_eext": 0.0,
              "E_el": -322.67020958080235,
              "E_en": -669.6483991732275,
              "E_kin": 334.1209683172977,
              "E_next": 0.0,
              "E_nn": 0.0,
              "E_nuc": 0.0,
              "E_tot": -322.67020958080235,
              "E_x": 0.0,
              "E_xc": -10.101960472150685,
              "Er_el": 0.0,
              "Er_nuc": 0.0,
              "Er_tot": 0.0
            },
            "energy_total": -322.67020958080235,
            "energy_update": 0.00019794353096358464,
            "mo_residual": 2.2535047269467475e-05,
            "wall_time": 13.366406987
          },
          {
            "energy_terms": {
              "E_ee": 22.95926260299848,
              "E_eext": 0.0,
              "E_el": -322.6703274782302,
              "E_en": -669.6537933048702,
              "E_kin": 334.12620169064456,
              "E_next": 0.0,
              "E_nn": 0.0,
              "E_nuc": 0.0,
              "E_tot": -322.6703274782302,
              "E_x": 0.0,
              "E_xc": -10.101998467003078,
              "Er_el": 0.0,
              "Er_nuc": 0.0,
              "Er_tot": 0.0
            },
            "energy_total": -322.6703274782302,
            "energy_update": 0.00011789742785595081,
            "mo_residual": 4.775447679287518e-06,
            "wall_time": 14.801000892
          },
          {
            "energy_terms": {
              "E_ee": 22.959256730793165,
              "E_eext": 0.0,
              "E_el": -322.6703751642602,
              "E_en": -669.6540618945498,
              "E_kin": 334.12642583902146,
              "E_next": 0.0,
              "E_nn": 0.0,
              "E_nuc": 0.0,
              "E_tot": -322.6703751642602,
              "E_x": 0.0,
              "E_xc": -10.101995839525003,
              "Er_el": 0.0,
              "Er_nuc": 0.0,
              "Er_tot": 0.0
            },
            "energy_total": -322.6703751642602,
            "energy_update": 4.768602997273774e-05,
            "mo_residual": 1.3875946177919933e-06,
            "wall_time": 15.735380046
          },
          {
            "energy_terms": {
              "E_ee": 22.959398141771487,
              "E_eext": 0.0,
              "E_el": -322.6697533350467,
              "E_en": -669.6593342068227,
              "E_kin": 334.13224442561176,
              "E_next": 0.0,
              "E_nn": 0.0,
              "E_nuc": 0.0,
              "E_tot": -322.6697533350467,
              "E_x": 0.0,
              "E_xc": -10.102061695607274,
              "Er_el": 0.0,
              "Er_nuc": 0.0,
              "Er_tot": 0.0
            },
            "energy_total": -322.6697533350467,
            "energy_update": 0.0006218292134576586,
            "mo_residual": 9.912954552232099e-06,
            "wall_time": 17.722493149
          },
          {
            "energy_terms": {
              "E_ee": 22.959232084126178,
              "E_eext": 0.0,
              "E_el": -322.6699079299442,
              "E_en": -669.6487946092496,
              "E_kin": 334.12163648153887,
              "E_next": 0.0,
              "E_nn": 0.0,
              "E_nuc": 0.0,
              "E_tot": -322.6699079299442,
              "E_x": 0.0,
              "E_xc": -10.1019818863596,
              "Er_el": 0.0,
              "Er_nuc": 0.0,
              "Er_tot": 0.0
            },
            "energy_total": -322.6699079299442,
            "energy_update": 0.00015459489748081978,
            "mo_residual": 8.167839595783602e-06,
            "wall_time": 14.958892648
          },
          {
            "energy_terms": {
              "E_ee": 22.959219783643036,
              "E_eext": 0.0,
              "E_el": -322.66999631680926,
              "E_en": -669.6501058077466,
              "E_kin": 334.1228677773179,
              "E_next": 0.0,
              "E_nn": 0.0,
              "E_nuc": 0.0,
              "E_tot": -322.66999631680926,
              "E_x": 0.0,
              "E_xc": -10.101978070023572,
              "Er_el": 0.0,
              "Er_nuc": 0.0,
              "Er_tot": 0.0
            },
            "energy_total": -322.66999631680926,
            "energy_update": 8.838686505896476e-05,
            "mo_residual": 1.8443922623925197e-06,
            "wall_time": 14.126496065
          },
          {
            "energy_terms": {
              "E_ee": 22.95917448316739,
              "E_eext": 0.0,
              "E_el": -322.6701530976504,
              "E_en": -669.6490763115463,
              "E_kin": 334.121706699754,
              "E_next": 0.0,
              "E_nn": 0.0,
              "E_nuc": 0.0,
              "E_tot": -322.6701530976504,
              "E_x": 0.0,
              "E_xc": -10.10195796902548,
              "Er_el": 0.0,
              "Er_nuc": 0.0,
              "Er_tot": 0.0
            },
            "energy_total": -322.6701530976504,
            "energy_update": 0.0001567808411664373,
            "mo_residual": 2.714753076172589e-06,
            "wall_time": 13.726287262
          },
          {
            "energy_terms": {
              "E_ee": 22.959087472481837,
              "E_eext": 0.0,
              "E_el": -322.67002949886495,
              "E_en": -669.6434604857455,
              "E_kin": 334.1162602768906,
              "E_next": 0.0,
              "E_nn": 0.0,
              "E_nuc": 0.0,
              "E_tot": -322.67002949886495,
              "E_x": 0.0,
              "E_xc": -10.10191676249186,
              "Er_el": 0.0,
              "Er_nuc": 0.0,
              "Er_tot": 0.0
            },
            "energy_total": -322.67002949886495,
            "energy_update": 0.00012359878547840708,
            "mo_residual": 4.201717664554791e-06,
            "wall_time": 15.561124923
          },
          {
            "energy_terms": {
              "E_ee": 22.95929382755055,
              "E_eext": 0.0,
              "E_el": -322.67030094751357,
              "E_en": -669.655827709054,
              "E_kin": 334.12824614062066,
              "E_next": 0.0,
              "E_nn": 0.0,
              "E_nuc": 0.0,
              "E_tot": -322.67030094751357,
              "E_x": 0.0,
              "E_xc": -10.102013206630712,
              "Er_el": 0.0,
              "Er_nuc": 0.0,
              "Er_tot": 0.0
            },
            "energy_total": -322.67030094751357,
            "energy_update": 0.0002714486486183887,
            "mo_residual": 9.561202962271512e-06,
            "wall_time": 15.966174234
          },
          {
            "energy_terms": {
              "E_ee": 22.959209885973348,
              "E_eext": 0.0,
              "E_el": -322.6703025905923,
              "E_en": -669.6499572515429,
              "E_kin": 334.1224172491192,
              "E_next": 0.0,
              "E_nn": 0.0,
              "E_nuc": 0.0,
              "E_tot": -322.6703025905923,
              "E_x": 0.0,
              "E_xc": -10.101972474141972,
              "Er_el": 0.0,
              "Er_nuc": 0.0,
              "Er_tot": 0.0
            },
            "energy_total": -322.6703025905923,
            "energy_update": 1.6430787468380004e-06,
            "mo_residual": 4.26904995598869e-06,
            "wall_time": 13.487921523
          },
          {
            "energy_terms": {
              "E_ee": 22.95923117833655,
              "E_eext": 0.0,
              "E_el": -322.67032101990424,
              "E_en": -669.6522007159386,
              "E_kin": 334.12463205696815,
              "E_next": 0.0,
              "E_nn": 0.0,
              "E_nuc": 0.0,
              "E_tot": -322.67032101990424,
              "E_x": 0.0,
              "E_xc": -10.101983539270286,
              "Er_el": 0.0,
              "Er_nuc": 0.0,
              "Er_tot": 0.0
            },
            "energy_total": -322.67032101990424,
            "energy_update": 1.84293119218637e-05,
            "mo_residual": 1.6611212432026918e-06,
            "wall_time": 13.368648309
          },
          {
            "energy_terms": {
              "E_ee": 22.95925050460944,
              "E_eext": 0.0,
              "E_el": -322.6703481633586,
              "E_en": -669.6538171024887,
              "E_kin": 334.1262115137128,
              "E_next": 0.0,
              "E_nn": 0.0,
              "E_nuc": 0.0,
              "E_tot": -322.6703481633586,
              "E_x": 0.0,
              "E_xc": -10.101993079192138,
              "Er_el": 0.0,
              "Er_nuc": 0.0,
              "Er_tot": 0.0
            },
            "energy_total": -322.6703481633586,
            "energy_update": 2.714345436061194e-05,
            "mo_residual": 1.216623198727729e-06,
            "wall_time": 13.726028206
          },
          {
            "energy_terms": {
              "E_ee": 22.95930148160158,
              "E_eext": 0.0,
              "E_el": -322.6704339738151,
              "E_en": -669.6570982359101,
              "E_kin": 334.1293794879719,
              "E_next": 0.0,
              "E_nn": 0.0,
              "E_nuc": 0.0,
              "E_tot": -322.6704339738151,
              "E_x": 0.0,
              "E_xc": -10.102016707478457,
              "Er_el": 0.0,
              "Er_nuc": 0.0,
              "Er_tot": 0.0
            },
            "energy_total": -322.6704339738151,
            "energy_update": 8.581045648270447e-05,
            "mo_residual": 3.3350186501280916e-06,
            "wall_time": 15.179816352
          },
          {
            "energy_terms": {
              "E_ee": 22.95929175233973,
              "E_eext": 0.0,
              "E_el": -322.6704428664649,
              "E_en": -669.656683255053,
              "E_kin": 334.12896074948753,
              "E_next": 0.0,
              "E_nn": 0.0,
              "E_nuc": 0.0,
              "E_tot": -322.6704428664649,
              "E_x": 0.0,
              "E_xc": -10.102012113239072,
              "Er_el": 0.0,
              "Er_nuc": 0.0,
              "Er_tot": 0.0
            },
            "energy_total": -322.6704428664649,
            "energy_update": 8.892649816516496e-06,
            "mo_residual": 5.616681821627733e-07,
            "wall_time": 16.141476206
          },
          {
            "energy_terms": {
              "E_ee": 22.959284853910184,
              "E_eext": 0.0,
              "E_el": -322.67044484224124,
              "E_en": -669.656157321353,
              "E_kin": 334.128436383412,
              "E_next": 0.0,
              "E_nn": 0.0,
              "E_nuc": 0.0,
              "E_tot": -322.67044484224124,
              "E_x": 0.0,
              "E_xc": -10.102008758210406,
              "Er_el": 0.0,
              "Er_nuc": 0.0,
              "Er_tot": 0.0
            },
            "energy_total": -322.67044484224124,
            "energy_update": 1.9757763425332087e-06,
            "mo_residual": 3.8536122680975784e-07,
            "wall_time": 14.18153376
          },
          {
            "energy_terms": {
              "E_ee": 22.95927927681843,
              "E_eext": 0.0,
              "E_el": -322.67044810153504,
              "E_en": -669.6558680357713,
              "E_kin": 334.12814684938604,
              "E_next": 0.0,
              "E_nn": 0.0,
              "E_nuc": 0.0,
              "E_tot": -322.67044810153504,
              "E_x": 0.0,
              "E_xc": -10.102006191968258,
              "Er_el": 0.0,
              "Er_nuc": 0.0,
              "Er_tot": 0.0
            },
            "energy_total": -322.67044810153504,
            "energy_update": 3.2592938055131526e-06,
            "mo_residual": 2.4886521532519647e-07,
            "wall_time": 14.714941578
          },
          {
            "energy_terms": {
              "E_ee": 22.959278222407555,
              "E_eext": 0.0,
              "E_el": -322.6704517401822,
              "E_en": -669.6558619128413,
              "E_kin": 334.12813773771865,
              "E_next": 0.0,
              "E_nn": 0.0,
              "E_nuc": 0.0,
              "E_tot": -322.6704517401822,
              "E_x": 0.0,
              "E_xc": -10.102005787467126,
              "Er_el": 0.0,
              "Er_nuc": 0.0,
              "Er_tot": 0.0
            },
            "energy_total": -322.6704517401822,
            "energy_update": 3.6386471720106783e-06,
            "mo_residual": 1.3575212129128388e-07,
            "wall_time": 14.905185943
          },
          {
            "energy_terms": {
              "E_ee": 22.959275762598562,
              "E_eext": 0.0,
              "E_el": -322.67045676748035,
              "E_en": -669.6556828317656,
              "E_kin": 334.1279549107428,
              "E_next": 0.0,
              "E_nn": 0.0,
              "E_nuc": 0.0,
              "E_tot": -322.67045676748035,
              "E_x": 0.0,
              "E_xc": -10.102004609056117,
              "Er_el": 0.0,
              "Er_nuc": 0.0,
              "Er_tot": 0.0
            },
            "energy_total": -322.67045676748035,
            "energy_update": 5.027298129789415e-06,
            "mo_residual": 2.0864428457761143e-07,
            "wall_time": 15.233048046
          },
          {
            "energy_terms": {
              "E_ee": 22.959292622688853,
              "E_eext": 0.0,
              "E_el": -322.67046812584596,
              "E_en": -669.6566333801377,
              "E_kin": 334.1288851088797,
              "E_next": 0.0,
              "E_nn": 0.0,
              "E_nuc": 0.0,
              "E_tot": -322.67046812584596,
              "E_x": 0.0,
              "E_xc": -10.102012477276762,
              "Er_el": 0.0,
              "Er_nuc": 0.0,
              "Er_tot": 0.0
            },
            "energy_total": -322.67046812584596,
            "energy_update": 1.1358365611613408e-05,
            "mo_residual": 8.211986229668374e-07,
            "wall_time": 16.224754686
          },
          {
            "energy_terms": {
              "E_ee": 22.959290174165826,
              "E_eext": 0.0,
              "E_el": -322.6704686695566,
              "E_en": -669.6564757987156,
              "E_kin": 334.12872823850734,
              "E_next": 0.0,
              "E_nn": 0.0,
              "E_nuc": 0.0,
              "E_tot": -322.6704686695566,
              "E_x": 0.0,
              "E_xc": -10.102011283514098,
              "Er_el": 0.0,
              "Er_nuc": 0.0,
              "Er_tot": 0.0
            },
            "energy_total": -322.6704686695566,
            "energy_update": 5.437106551653414e-07,
            "mo_residual": 1.3099041553286944e-07,
            "wall_time": 14.395857479
          },
          {
            "energy_terms": {
              "E_ee": 22.958966895068848,
              "E_eext": 0.0,
              "E_el": -322.67041305383935,
              "E_en": -669.6374488111718,
              "E_kin": 334.109926656889,
              "E_next": 0.0,
              "E_nn": 0.0,
              "E_nuc": 0.0,
              "E_tot": -322.67041305383935,
              "E_x": 0.0,
              "E_xc": -10.101857794625413,
              "Er_el": 0.0,
              "Er_nuc": 0.0,
              "Er_tot": 0.0
            },
            "energy_total": -322.67041305383935,
            "energy_update": 5.561571725820613e-05,
            "mo_residual": 1.4633648936473351e-05,
            "wall_time": 19.203281096
          },
          {
            "energy_terms": {
              "E_ee": 22.959298056685224,
              "E_eext": 0.0,
              "E_el": -322.670468531707,
              "E_en": -669.6569371504863,
              "E_kin": 334.1291855565652,
              "E_next": 0.0,
              "E_nn": 0.0,
              "E_nuc": 0.0,
              "E_tot": -322.670468531707,
              "E_x": 0.0,
              "E_xc": -10.102014994471045,
              "Er_el": 0.0,
              "Er_nuc": 0.0,
              "Er_tot": 0.0
            },
            "energy_total": -322.670468531707,
            "energy_update": 5.547786764736884e-05,
            "mo_residual": 1.496742619250904e-05,
            "wall_time": 17.691042651
          },
          {
            "energy_terms": {
              "E_ee": 22.959254677450563,
              "E_eext": 0.0,
              "E_el": -322.6704710144601,
              "E_en": -669.6545369082453,
              "E_kin": 334.1268058963345,
              "E_next": 0.0,
              "E_nn": 0.0,
              "E_nuc": 0.0,
              "E_tot": -322.6704710144601,
              "E_x": 0.0,
              "E_xc": -10.101994679999873,
              "Er_el": 0.0,
              "Er_nuc": 0.0,
              "Er_tot": 0.0
            },
            "energy_total": -322.6704710144601,
            "energy_update": 2.48275307512813e-06,
            "mo_residual": 1.8238510851070062e-06,
            "wall_time": 15.994611283
          },
          {
            "energy_terms": {
              "E_ee": 22.959274192541837,
              "E_eext": 0.0,
              "E_el": -322.67047050662063,
              "E_en": -669.6556409404532,
              "E_kin": 334.12790008473814,
              "E_next": 0.0,
              "E_nn": 0.0,
              "E_nuc": 0.0,
              "E_tot": -322.67047050662063,
              "E_x": 0.0,
              "E_xc": -10.10200384344742,
              "Er_el": 0.0,
              "Er_nuc": 0.0,
              "Er_tot": 0.0
            },
            "energy_total": -322.67047050662063,
            "energy_update": 5.07839445162972e-07,
            "mo_residual": 8.297745314122063e-07,
            "wall_time": 16.326523074
          },
          {
            "energy_terms": {
              "E_ee": 22.959275806714913,
              "E_eext": 0.0,
              "E_el": -322.6704707413401,
              "E_en": -669.6557550984147,
              "E_kin": 334.1280131765285,
              "E_next": 0.0,
              "E_nn": 0.0,
              "E_nuc": 0.0,
              "E_tot": -322.6704707413401,
              "E_x": 0.0,
              "E_xc": -10.102004626168833,
              "Er_el": 0.0,
              "Er_nuc": 0.0,
              "Er_tot": 0.0
            },
            "energy_total": -322.6704707413401,
            "energy_update": 2.3471949361919542e-07,
            "mo_residual": 8.2316988595155e-08,
            "wall_time": 14.61028178
          },
          {
            "energy_terms": {
              "E_ee": 22.959276765667088,
              "E_eext": 0.0,
              "E_el": -322.67047102996975,
              "E_en": -669.655797078834,
              "E_kin": 334.12805434382375,
              "E_next": 0.0,
              "E_nn": 0.0,
              "E_nuc": 0.0,
              "E_tot": -322.67047102996975,
              "E_x": 0.0,
              "E_xc": -10.102005060626572,
              "Er_el": 0.0,
              "Er_nuc": 0.0,
              "Er_tot": 0.0
            },
            "energy_total": -322.67047102996975,
            "energy_update": 2.8862962153652916e-07,
            "mo_residual": 3.74848434293853e-08,
            "wall_time": 15.030893769
          },
          {
            "energy_terms": {
              "E_ee": 22.95927759442351,
              "E_eext": 0.0,
              "E_el": -322.67047148888884,
              "E_en": -669.6558337373933,
              "E_kin": 334.1280900854737,
              "E_next": 0.0,
              "E_nn": 0.0,
              "E_nuc": 0.0,
              "E_tot": -322.67047148888884,
              "E_x": 0.0,
              "E_xc": -10.102005431392689,
              "Er_el": 0.0,
              "Er_nuc": 0.0,
              "Er_tot": 0.0
            },
            "energy_total": -322.67047148888884,
            "energy_update": 4.589190893966588e-07,
            "mo_residual": 3.676610146277344e-08,
            "wall_time": 15.384384008
          },
          {
            "energy_terms": {
              "E_ee": 22.959275519206514,
              "E_eext": 0.0,
              "E_el": -322.6704716997559,
              "E_en": -669.6557171482069,
              "E_kin": 334.127974387307,
              "E_next": 0.0,
              "E_nn": 0.0,
              "E_nuc": 0.0,
              "E_tot": -322.6704716997559,
              "E_x": 0.0,
              "E_xc": -10.102004458062547,
              "Er_el": 0.0,
              "Er_nuc": 0.0,
              "Er_tot": 0.0
            },
            "energy_total": -322.6704716997559,
            "energy_update": 2.108670855704986e-07,
            "mo_residual": 8.832591116768136e-08,
            "wall_time": 15.703802785
          },
          {
            "energy_terms": {
              "E_ee": 22.959270020107517,
              "E_eext": 0.0,
              "E_el": -322.6704744249594,
              "E_en": -669.6554280552818,
              "E_kin": 334.12768548695533,
              "E_next": 0.0,
              "E_nn": 0.0,
              "E_nuc": 0.0,
              "E_tot": -322.6704744249594,
              "E_x": 0.0,
              "E_xc": -10.10200187674044,
              "Er_el": 0.0,
              "Er_nuc": 0.0,
              "Er_tot": 0.0
            },
            "energy_total": -322.6704744249594,
            "energy_update": 2.725203501086071e-06,
            "mo_residual": 2.7787741057397104e-07,
            "wall_time": 17.18867444
          },
          {
            "energy_terms": {
              "E_ee": 22.95927824385667,
              "E_eext": 0.0,
              "E_el": -322.6704747386371,
              "E_en": -669.6560226483327,
              "E_kin": 334.12827554149374,
              "E_next": 0.0,
              "E_nn": 0.0,
              "E_nuc": 0.0,
              "E_tot": -322.6704747386371,
              "E_x": 0.0,
              "E_xc": -10.102005875654768,
              "Er_el": 0.0,
              "Er_nuc": 0.0,
              "Er_tot": 0.0
            },
            "energy_total": -322.6704747386371,
            "energy_update": 3.136776740575442e-07,
            "mo_residual": 4.2727311801037416e-07,
            "wall_time": 15.705667608
          },
          {
            "energy_terms": {
              "E_ee": 22.959303949517462,
              "E_eext": 0.0,
              "E_el": -322.67047497453717,
              "E_en": -669.6575045987572,
              "E_kin": 334.12974363737237,
              "E_next": 0.0,
              "E_nn": 0.0,
              "E_nuc": 0.0,
              "E_tot": -322.67047497453717,
              "E_x": 0.0,
              "E_xc": -10.102017962669796,
              "Er_el": 0.0,
              "Er_nuc": 0.0,
              "Er_tot": 0.0
            },
            "energy_total": -322.67047497453717,
            "energy_update": 2.3590007458551554e-07,
            "mo_residual": 1.1031531017255954e-06,
            "wall_time": 16.286171647
          },
          {
            "energy_terms": {
              "E_ee": 22.959285937861573,
              "E_eext": 0.0,
              "E_el": -322.6704748803035,
              "E_en": -669.6563417250376,
              "E_kin": 334.1285902482364,
              "E_next": 0.0,
              "E_nn": 0.0,
              "E_nuc": 0.0,
              "E_tot": -322.6704748803035,
              "E_x": 0.0,
              "E_xc": -10.102009341363923,
              "Er_el": 0.0,
              "Er_nuc": 0.0,
              "Er_tot": 0.0
            },
            "energy_total": -322.6704748803035,
            "energy_update": 9.423365554539487e-08,
            "mo_residual": 8.462980214168846e-07,
            "wall_time": 16.70197246
          }
        ],
        "wall_time": 573.183554995
      },
      "success": true
    },
    "schema_name": "mrchem_output",
    "schema_version": 1,
    "success": true
  }
}
