{
  "input": {
    "molecule": {
      "cavity_coords": [
        {
          "center": [
            0.0,
            0.0,
            0.0
          ],
          "radius": 1.03
        }
      ],
      "cavity_width": 0.2,
      "charge": 0,
      "coords": [
        {
          "atom": "kr",
          "xyz": [
            0.0,
            0.0,
            0.0
          ]
        }
      ],
      "multiplicity": 1
    },
    "mpi": {
      "bank_size": 1,
      "numerically_exact": false,
      "shared_memory_size": 10000
    },
    "mra": {
      "basis_order": 9,
      "basis_type": "interpolating",
      "boxes": [
        2,
        2,
        2
      ],
      "corner": [
        -1,
        -1,
        -1
      ],
      "max_scale": 20,
      "min_scale": -7
    },
    "printer": {
      "file_name": "Kr_101.inp",
      "print_level": 0,
      "print_mpi": false,
      "print_prec": 6,
      "print_width": 75
    },
    "rsp_calculations": {},
    "scf_calculation": {
      "fock_operator": {
        "coulomb_operator": {
          "poisson_prec": 1e-06,
          "shared_memory": false
        },
        "exchange_operator": {
          "exchange_prec": -1.0,
          "poisson_prec": 1e-06
        },
        "kinetic_operator": {
          "derivative": "abgv_55"
        },
        "nuclear_operator": {
          "proj_prec": 1e-06,
          "shared_memory": false,
          "smooth_prec": 1e-06
        },
        "xc_operator": {
          "shared_memory": false,
          "xc_functional": {
            "cutoff": 0.0,
            "functionals": [
              {
                "coef": 1.0,
                "name": "pbe"
              }
            ],
            "spin": false
          }
        },
        "zora_operator": {
          "derivative": "abgv_00",
          "include_coulomb": false,
          "include_nuclear": true,
          "include_xc": true,
          "light_speed": -1.0,
          "proj_prec": 1e-06,
          "shared_memory": false
        }
      },
      "initial_guess": {
        "file_CUBE_a": "cube_vectors/CUBE_a_vector.json",
        "file_CUBE_b": "cube_vectors/CUBE_b_vector.json",
        "file_CUBE_p": "cube_vectors/CUBE_p_vector.json",
        "file_basis": "initial_guess/mrchem.bas",
        "file_chk": "checkpoint/phi_scf",
        "file_gto_a": "initial_guess/mrchem.moa",
        "file_gto_b": "initial_guess/mrchem.mob",
        "file_gto_p": "initial_guess/mrchem.mop",
        "file_phi_a": "initial_guess/phi_a_scf",
        "file_phi_b": "initial_guess/phi_b_scf",
        "file_phi_p": "initial_guess/phi_p_scf",
        "localize": true,
        "method": "DFT (PBE)",
        "prec": 1e-05,
        "relativity": "ZORA (V_nuc + V_xc)",
        "restricted": true,
        "screen": 12.0,
        "type": "sad_gto",
        "zeta": 0
      },
      "properties": {
        "dipole_moment": {
          "dip-1": {
            "operator": "h_e_dip",
            "precision": 1e-06,
            "r_O": [
              0.0,
              0.0,
              0.0
            ]
          }
        }
      },
      "scf_solver": {
        "checkpoint": false,
        "derivative": "abgv_55",
        "energy_thrs": -1.0,
        "file_chk": "checkpoint/phi_scf",
        "final_prec": 1e-06,
        "helmholtz_prec": -1.0,
        "kain": 6,
        "light_speed": -1.0,
        "localize": true,
        "max_iter": 100,
        "method": "DFT (PBE)",
        "orbital_thrs": 1e-05,
        "proj_prec": 1e-06,
        "relativity": "ZORA (V_nuc + V_xc)",
        "rotation": 0,
        "shared_memory": false,
        "smooth_prec": 1e-06,
        "start_prec": 1e-06
      }
    },
    "schema_name": "mrchem_input",
    "schema_version": 1
  },
  "output": {
    "properties": {
      "center_of_mass": [
        0.0,
        0.0,
        0.0
      ],
      "charge": 0,
      "dipole_moment": {
        "dip-1": {
          "magnitude": 2.07243602943759e-06,
          "r_O": [
            0.0,
            0.0,
            0.0
          ],
          "vector": [
            -1.5780740650301273e-06,
            5.616478517020446e-08,
            1.3422067122083386e-06
          ],
          "vector_el": [
            -1.5788744313627312e-06,
            5.5362185089752325e-08,
            1.3414017590029914e-06
          ],
          "vector_nuc": [
            8.003663326039102e-10,
            8.02600080452137e-10,
            8.04953205347162e-10
          ]
        }
      },
      "geometry": [
        {
          "symbol": "Kr",
          "xyz": [
            0.0,
            0.0,
            0.0
          ]
        }
      ],
      "multiplicity": 1,
      "orbital_energies": {
        "energy": [
          -531.2863547067894,
          -69.01001428322883,
          -60.9451549807173,
          -60.94515492996203,
          -60.94515486885983,
          -9.748252700795632,
          -7.197450119833464,
          -7.197450034992637,
          -7.197449950291208,
          -2.989104333842237,
          -2.9891043116010603,
          -2.989104276786321,
          -2.9891039516569724,
          -2.989103865910314,
          -0.8503915752509469,
          -0.3400675496471808,
          -0.34006754374273657,
          -0.34006753486709346
        ],
        "occupation": [
          2.0,
          2.0,
          2.0,
          2.0,
          2.0,
          2.0,
          2.0,
          2.0,
          2.0,
          2.0,
          2.0,
          2.0,
          2.0,
          2.0,
          2.0,
          2.0,
          2.0,
          2.0
        ],
        "spin": [
          "p",
          "p",
          "p",
          "p",
          "p",
          "p",
          "p",
          "p",
          "p",
          "p",
          "p",
          "p",
          "p",
          "p",
          "p",
          "p",
          "p",
          "p"
        ],
        "sum_occupied": -1662.5771030375504
      },
      "scf_energy": {
        "E_ee": 1186.7607115885385,
        "E_eext": 0.0,
        "E_el": -2820.0356842349147,
        "E_en": -6796.981699085683,
        "E_kin": 2887.3067711080685,
        "E_next": 0.0,
        "E_nn": 0.0,
        "E_nuc": 0.0,
        "E_tot": -2820.0356842349147,
        "E_x": 0.0,
        "E_xc": -97.12146784583817,
        "Er_el": 0.0,
        "Er_nuc": 0.0,
        "Er_tot": 0.0
      }
    },
    "provenance": {
      "creator": "MRChem",
      "mpi_processes": 1,
      "nthreads": 18,
      "routine": "mrchem.x",
      "total_cores": 18,
      "version": "1.1.0-alpha"
    },
    "rsp_calculations": null,
    "scf_calculation": {
      "initial_energy": {
        "E_ee": 1173.756798920255,
        "E_eext": 0.0,
        "E_el": -2798.6745268640384,
        "E_en": -6562.455971137306,
        "E_kin": 2685.189013809382,
        "E_next": 0.0,
        "E_nn": 0.0,
        "E_nuc": 0.0,
        "E_tot": -2798.6745268640384,
        "E_x": 0.0,
        "E_xc": -95.16436845636939,
        "Er_el": 0.0,
        "Er_nuc": 0.0,
        "Er_tot": 0.0
      },
      "scf_solver": {
        "converged": true,
        "cycles": [
          {
            "energy_terms": {
              "E_ee": 1179.0385136678187,
              "E_eext": 0.0,
              "E_el": -2818.4596658560354,
              "E_en": -6686.038028146762,
              "E_kin": 2784.604338313422,
              "E_next": 0.0,
              "E_nn": 0.0,
              "E_nuc": 0.0,
              "E_tot": -2818.4596658560354,
              "E_x": 0.0,
              "E_xc": -96.0644896905139,
              "Er_el": 0.0,
              "Er_nuc": 0.0,
              "Er_tot": 0.0
            },
            "energy_total": -2818.4596658560354,
            "energy_update": 19.785138991996973,
            "mo_residual": 0.16280515526504352,
            "wall_time": 105.813097606
          },
          {
            "energy_terms": {
              "E_ee": 1182.5563665751952,
              "E_eext": 0.0,
              "E_el": -2819.672936044754,
              "E_en": -6739.752371516708,
              "E_kin": 2834.085429597367,
              "E_next": 0.0,
              "E_nn": 0.0,
              "E_nuc": 0.0,
              "E_tot": -2819.672936044754,
              "E_x": 0.0,
              "E_xc": -96.56236070060794,
              "Er_el": 0.0,
              "Er_nuc": 0.0,
              "Er_tot": 0.0
            },
            "energy_total": -2819.672936044754,
            "energy_update": 1.2132701887185249,
            "mo_residual": 0.058566156401422,
            "wall_time": 119.571977617
          },
          {
            "energy_terms": {
              "E_ee": 1184.5097823911126,
              "E_eext": 0.0,
              "E_el": -2819.922023398078,
              "E_en": -6766.989683445629,
              "E_kin": 2859.384736676682,
              "E_next": 0.0,
              "E_nn": 0.0,
              "E_nuc": 0.0,
              "E_tot": -2819.922023398078,
              "E_x": 0.0,
              "E_xc": -96.82685902024362,
              "Er_el": 0.0,
              "Er_nuc": 0.0,
              "Er_tot": 0.0
            },
            "energy_total": -2819.922023398078,
            "energy_update": 0.24908735332428478,
            "mo_residual": 0.029718784198188405,
            "wall_time": 113.146499522
          },
          {
            "energy_terms": {
              "E_ee": 1186.3709187765264,
              "E_eext": 0.0,
              "E_el": -2819.858234192597,
              "E_en": -6798.638667377177,
              "E_kin": 2889.5096804774616,
              "E_next": 0.0,
              "E_nn": 0.0,
              "E_nuc": 0.0,
              "E_tot": -2819.858234192597,
              "E_x": 0.0,
              "E_xc": -97.10016606940871,
              "Er_el": 0.0,
              "Er_nuc": 0.0,
              "Er_tot": 0.0
            },
            "energy_total": -2819.858234192597,
            "energy_update": 0.06378920548104361,
            "mo_residual": 0.030848382133392735,
            "wall_time": 122.330912154
          },
          {
            "energy_terms": {
              "E_ee": 1186.8741573012064,
              "E_eext": 0.0,
              "E_el": -2820.002387058666,
              "E_en": -6796.7115018509785,
              "E_kin": 2886.9676221491973,
              "E_next": 0.0,
              "E_nn": 0.0,
              "E_nuc": 0.0,
              "E_tot": -2820.002387058666,
              "E_x": 0.0,
              "E_xc": -97.13266465809133,
              "Er_el": 0.0,
              "Er_nuc": 0.0,
              "Er_tot": 0.0
            },
            "energy_total": -2820.002387058666,
            "energy_update": 0.14415286606890731,
            "mo_residual": 0.012802019519719312,
            "wall_time": 124.960339194
          },
          {
            "energy_terms": {
              "E_ee": 1186.8550911484251,
              "E_eext": 0.0,
              "E_el": -2820.0064844700432,
              "E_en": -6798.613716033252,
              "E_kin": 2888.8862994882907,
              "E_next": 0.0,
              "E_nn": 0.0,
              "E_nuc": 0.0,
              "E_tot": -2820.0064844700432,
              "E_x": 0.0,
              "E_xc": -97.13415907350686,
              "Er_el": 0.0,
              "Er_nuc": 0.0,
              "Er_tot": 0.0
            },
            "energy_total": -2820.0064844700432,
            "energy_update": 0.004097411377188109,
            "mo_residual": 0.006761128607535083,
            "wall_time": 123.229848438
          },
          {
            "energy_terms": {
              "E_ee": 1186.8615232382972,
              "E_eext": 0.0,
              "E_el": -2819.9058470780433,
              "E_en": -6801.938738164641,
              "E_kin": 2892.316861503195,
              "E_next": 0.0,
              "E_nn": 0.0,
              "E_nuc": 0.0,
              "E_tot": -2819.9058470780433,
              "E_x": 0.0,
              "E_xc": -97.14549365489421,
              "Er_el": 0.0,
              "Er_nuc": 0.0,
              "Er_tot": 0.0
            },
            "energy_total": -2819.9058470780433,
            "energy_update": 0.10063739199995325,
            "mo_residual": 0.004056186100196175,
            "wall_time": 128.807471524
          },
          {
            "energy_terms": {
              "E_ee": 1186.7829886520085,
              "E_eext": 0.0,
              "E_el": -2820.0239980209617,
              "E_en": -6795.286323988694,
              "E_kin": 2885.595594325604,
              "E_next": 0.0,
              "E_nn": 0.0,
              "E_nuc": 0.0,
              "E_tot": -2820.0239980209617,
              "E_x": 0.0,
              "E_xc": -97.11625700988053,
              "Er_el": 0.0,
              "Er_nuc": 0.0,
              "Er_tot": 0.0
            },
            "energy_total": -2820.0239980209617,
            "energy_update": 0.11815094291841888,
            "mo_residual": 0.0018961034399739586,
            "wall_time": 129.792212517
          },
          {
            "energy_terms": {
              "E_ee": 1186.7556192657148,
              "E_eext": 0.0,
              "E_el": -2820.0099489071445,
              "E_en": -6795.49347081034,
              "E_kin": 2885.842702360364,
              "E_next": 0.0,
              "E_nn": 0.0,
              "E_nuc": 0.0,
              "E_tot": -2820.0099489071445,
              "E_x": 0.0,
              "E_xc": -97.11479972288313,
              "Er_el": 0.0,
              "Er_nuc": 0.0,
              "Er_tot": 0.0
            },
            "energy_total": -2820.0099489071445,
            "energy_update": 0.014049113817236503,
            "mo_residual": 0.0010198289416112523,
            "wall_time": 127.605587101
          },
          {
            "energy_terms": {
              "E_ee": 1186.7859069966203,
              "E_eext": 0.0,
              "E_el": -2819.985480093081,
              "E_en": -6799.294895720025,
              "E_kin": 2889.6544829240443,
              "E_next": 0.0,
              "E_nn": 0.0,
              "E_nuc": 0.0,
              "E_tot": -2819.985480093081,
              "E_x": 0.0,
              "E_xc": -97.13097429372064,
              "Er_el": 0.0,
              "Er_nuc": 0.0,
              "Er_tot": 0.0
            },
            "energy_total": -2819.985480093081,
            "energy_update": 0.024468814063311584,
            "mo_residual": 0.0008583622925257185,
            "wall_time": 126.040593034
          },
          {
            "energy_terms": {
              "E_ee": 1186.7615589352079,
              "E_eext": 0.0,
              "E_el": -2820.019605343196,
              "E_en": -6797.835853244267,
              "E_kin": 2888.1792262938034,
              "E_next": 0.0,
              "E_nn": 0.0,
              "E_nuc": 0.0,
              "E_tot": -2820.019605343196,
              "E_x": 0.0,
              "E_xc": -97.12453732794025,
              "Er_el": 0.0,
              "Er_nuc": 0.0,
              "Er_tot": 0.0
            },
            "energy_total": -2820.019605343196,
            "energy_update": 0.034125250114811934,
            "mo_residual": 0.0006501195333768584,
            "wall_time": 125.425655827
          },
          {
            "energy_terms": {
              "E_ee": 1186.746838443623,
              "E_eext": 0.0,
              "E_el": -2820.0172273574503,
              "E_en": -6795.7853348152275,
              "E_kin": 2886.137129687631,
              "E_next": 0.0,
              "E_nn": 0.0,
              "E_nuc": 0.0,
              "E_tot": -2820.0172273574503,
              "E_x": 0.0,
              "E_xc": -97.11586067347669,
              "Er_el": 0.0,
              "Er_nuc": 0.0,
              "Er_tot": 0.0
            },
            "energy_total": -2820.0172273574503,
            "energy_update": 0.0023779857456247555,
            "mo_residual": 0.00038001775679619637,
            "wall_time": 126.395146639
          },
          {
            "energy_terms": {
              "E_ee": 1186.7546553789825,
              "E_eext": 0.0,
              "E_el": -2820.034932915197,
              "E_en": -6796.743943265336,
              "E_kin": 2887.074427303962,
              "E_next": 0.0,
              "E_nn": 0.0,
              "E_nuc": 0.0,
              "E_tot": -2820.034932915197,
              "E_x": 0.0,
              "E_xc": -97.12007233280477,
              "Er_el": 0.0,
              "Er_nuc": 0.0,
              "Er_tot": 0.0
            },
            "energy_total": -2820.034932915197,
            "energy_update": 0.017705557746467093,
            "mo_residual": 0.00022064751511293143,
            "wall_time": 125.772740509
          },
          {
            "energy_terms": {
              "E_ee": 1186.757037416686,
              "E_eext": 0.0,
              "E_el": -2820.0351300997063,
              "E_en": -6796.8540502666965,
              "E_kin": 2887.182580931109,
              "E_next": 0.0,
              "E_nn": 0.0,
              "E_nuc": 0.0,
              "E_tot": -2820.0351300997063,
              "E_x": 0.0,
              "E_xc": -97.12069818080431,
              "Er_el": 0.0,
              "Er_nuc": 0.0,
              "Er_tot": 0.0
            },
            "energy_total": -2820.0351300997063,
            "energy_update": 0.00019718450948857935,
            "mo_residual": 7.407763195018053e-05,
            "wall_time": 124.546211418
          },
          {
            "energy_terms": {
              "E_ee": 1186.7623677286977,
              "E_eext": 0.0,
              "E_el": -2820.0353291759707,
              "E_en": -6797.181581370622,
              "E_kin": 2887.5062453656287,
              "E_next": 0.0,
              "E_nn": 0.0,
              "E_nuc": 0.0,
              "E_tot": -2820.0353291759707,
              "E_x": 0.0,
              "E_xc": -97.12236089967571,
              "Er_el": 0.0,
              "Er_nuc": 0.0,
              "Er_tot": 0.0
            },
            "energy_total": -2820.0353291759707,
            "energy_update": 0.0001990762643799826,
            "mo_residual": 8.750635790753466e-05,
            "wall_time": 123.246435371
          },
          {
            "energy_terms": {
              "E_ee": 1186.7599498407546,
              "E_eext": 0.0,
              "E_el": -2820.035400181344,
              "E_en": -6796.916294797753,
              "E_kin": 2887.242123557656,
              "E_next": 0.0,
              "E_nn": 0.0,
              "E_nuc": 0.0,
              "E_tot": -2820.035400181344,
              "E_x": 0.0,
              "E_xc": -97.12117878200188,
              "Er_el": 0.0,
              "Er_nuc": 0.0,
              "Er_tot": 0.0
            },
            "energy_total": -2820.035400181344,
            "energy_update": 7.100537322912714e-05,
            "mo_residual": 5.0274841674017646e-05,
            "wall_time": 126.417092237
          },
          {
            "energy_terms": {
              "E_ee": 1186.7611784172284,
              "E_eext": 0.0,
              "E_el": -2820.0358833034793,
              "E_en": -6797.030950501659,
              "E_kin": 2887.355578106517,
              "E_next": 0.0,
              "E_nn": 0.0,
              "E_nuc": 0.0,
              "E_tot": -2820.0358833034793,
              "E_x": 0.0,
              "E_xc": -97.1216893255653,
              "Er_el": 0.0,
              "Er_nuc": 0.0,
              "Er_tot": 0.0
            },
            "energy_total": -2820.0358833034793,
            "energy_update": 0.0004831221353924775,
            "mo_residual": 2.3266899417405934e-05,
            "wall_time": 124.847687755
          },
          {
            "energy_terms": {
              "E_ee": 1186.7607115885385,
              "E_eext": 0.0,
              "E_el": -2820.0356842349147,
              "E_en": -6796.981699085683,
              "E_kin": 2887.3067711080685,
              "E_next": 0.0,
              "E_nn": 0.0,
              "E_nuc": 0.0,
              "E_tot": -2820.0356842349147,
              "E_x": 0.0,
              "E_xc": -97.12146784583817,
              "Er_el": 0.0,
              "Er_nuc": 0.0,
              "Er_tot": 0.0
            },
            "energy_total": -2820.0356842349147,
            "energy_update": 0.0001990685645978374,
            "mo_residual": 1.1965216586966833e-05,
            "wall_time": 129.40250671
          }
        ],
        "wall_time": 2227.355337759
      },
      "success": true
    },
    "schema_name": "mrchem_output",
    "schema_version": 1,
    "success": true
  }
}
